setup.py
./total/__init__.py
./total/total.py
total/__init__.py
total/total.py
total.egg-info/PKG-INFO
total.egg-info/SOURCES.txt
total.egg-info/dependency_links.txt
total.egg-info/entry_points.txt
total.egg-info/top_level.txt