Metadata-Version: 1.0
Name: total
Version: 0.0.4
Summary: Simple AWK tasks, made awesome
Home-page: https://github.com/daniellawrence/total
Author: Danny Lawrence
Author-email: dannyla@linux.com
License: UNKNOWN
Platform: UNKNOWN
